{
  "type": "FanCode All Live Matches Data in Json",
  "generated_by": "Byte Capsule \nTelegram: https://t.me/J_9X_H_9X_N\nGithub:https://github.com/byte-capsule",
  "total_mathes": 6,
  "last_upaded": "05-10-2024 on 7:14:43 PM \ud83c\udf19",
  "matches": [
    {
      "event_catagory": "cricket",
      "event_name": "Dream11 European Cricket Championship, 2024",
      "match_id": 109489,
      "match_name": "Ireland XI vs Scotland XI",
      "team_1": "Ireland XI",
      "team_1_flag": "https://d13ir53smqqeyp.cloudfront.net/flags/cr-flags/FC-IRE@2x.png",
      "team_2": "Scotland XI",
      "team_2_flag": "https://d13ir53smqqeyp.cloudfront.net/flags/cr-flags/FC-SCO@2x.png",
      "banner": "https://www.fancode.com/aig/match/v1/109489_CASACARDS_APP.png",
      "stream_link": "https://dai.google.com/linear/hls/event/ZW1Wk1uYTianrnqGh67Kdg/master.m3u8"
    },
    {
      "event_catagory": "cricket",
      "event_name": "ICC Cricket World Cup Challenge League, 2024-26",
      "match_id": 108426,
      "match_name": "Jersey vs Denmark",
      "team_1": "Jersey",
      "team_1_flag": "https://d13ir53smqqeyp.cloudfront.net/flags/cr-flags/FC-JERSE@2x.png",
      "team_2": "Denmark",
      "team_2_flag": "https://d13ir53smqqeyp.cloudfront.net/flags/cr-flags/FC-DEN@2x.png",
      "banner": "https://www.fancode.com/skillup-uploads/cms-media/108426_4464_JER_DEN_fc-web.jpg",
      "stream_link": "https://dai.google.com/linear/hls/event/6Wy2PVUSQoic0mTp--9lLA/master.m3u8"
    },
    {
      "event_catagory": "cricket",
      "event_name": "ICC Cricket World Cup Challenge League, 2024-26",
      "match_id": 108425,
      "match_name": "Kenya vs Papua New Guinea",
      "team_1": "Kenya",
      "team_1_flag": "https://d13ir53smqqeyp.cloudfront.net/flags/cr-flags/FC-KNA@2x.png",
      "team_2": "Papua New Guinea",
      "team_2_flag": "https://d13ir53smqqeyp.cloudfront.net/flags/cr-flags/FC-PNG@2x.png",
      "banner": "https://www.fancode.com/skillup-uploads/cms-media/108425_4464_KEN_PNG_fc-web.jpg",
      "stream_link": "https://dai.google.com/linear/hls/event/NRz8lTZpRHy5LH226Abzfw/master.m3u8"
    },
    {
      "event_catagory": "cricket",
      "event_name": "United Arab Emirates and USA tour of Namibia, 2024",
      "match_id": 109590,
      "match_name": "Namibia vs USA",
      "team_1": "Namibia",
      "team_1_flag": "https://d13ir53smqqeyp.cloudfront.net/flags/cr-flags/FC-NAM@2x.png",
      "team_2": "USA",
      "team_2_flag": "https://d13ir53smqqeyp.cloudfront.net/flags/cr-flags/FC-USA@2x.png",
      "banner": "https://www.fancode.com/skillup-uploads/cms-media/Namibia-vs-USA_old_1727439531792.jpg",
      "stream_link": "https://dai.google.com/linear/hls/event/MpDHCwr1RwiuR5-lD9hT4Q/master.m3u8"
    },
    {
      "event_catagory": "football",
      "event_name": "EFL Championship 2024-25",
      "match_id": 109810,
      "match_name": "Burnley vs Preston North End",
      "team_1": "Burnley",
      "team_1_flag": "https://d13ir53smqqeyp.cloudfront.net/flags/ft-flags/FC-BURNL@2x.png",
      "team_2": "Preston North End",
      "team_2_flag": "https://d13ir53smqqeyp.cloudfront.net/flags/ft-flags/FC-PREST@2x.png",
      "banner": "https://www.fancode.com/skillup-uploads/cms-media/BUR-vs-PRE_fc-web-2.jpg",
      "stream_link": "https://dai.google.com/linear/hls/event/6rxfAIgQQEyZQBeUcRixfQ/master.m3u8"
    },
    {
      "event_catagory": "golf",
      "event_name": "Alfred Dunhill Links Championship",
      "match_id": 110038,
      "match_name": "Day 3",
      "team_1": "Day 3",
      "team_1_flag": "https://d13ir53smqqeyp.cloudfront.net/flags/gl-flags/FC-AD@2x.png",
      "team_2": "Scotland",
      "team_2_flag": "https://d13ir53smqqeyp.cloudfront.net/flags/gl-flags/FC-LOC@2x.png",
      "banner": "https://www.fancode.com/skillup-uploads/cms-media/Alfred-Dunhill-Links-Championship_match_card_1.jpg",
      "stream_link": "https://dai.google.com/linear/hls/event/m01KJ7LFTKGI4cV84_KSxQ/master.m3u8"
    }
  ]
}