{
  "type": "FanCode All Live Matches Data in Json",
  "generated_by": "Byte Capsule \nTelegram: https://t.me/J_9X_H_9X_N\nGithub:https://github.com/byte-capsule",
  "total_mathes": 2,
  "last_upaded": "06-10-2024 on 6:17:11 PM \ud83c\udf19",
  "matches": [
    {
      "event_catagory": "cricket",
      "event_name": "Dream11 European Cricket Championship, 2024",
      "match_id": 109500,
      "match_name": "Denmark vs Germany",
      "team_1": "Denmark",
      "team_1_flag": "https://d13ir53smqqeyp.cloudfront.net/flags/cr-flags/FC-DEN@2x.png",
      "team_2": "Germany",
      "team_2_flag": "https://d13ir53smqqeyp.cloudfront.net/flags/cr-flags/FC-GER@2x.png",
      "banner": "https://www.fancode.com/skillup-uploads/cms-media/109500_4514_GER_DEN_fc-web.jpg",
      "stream_link": "https://dai.google.com/linear/hls/event/mR9ILqIGSnu7WPMi6q70Yg/master.m3u8"
    },
    {
      "event_catagory": "golf",
      "event_name": "Alfred Dunhill Links Championship",
      "match_id": 110039,
      "match_name": "Day 4",
      "team_1": "Day 4",
      "team_1_flag": "https://d13ir53smqqeyp.cloudfront.net/flags/gl-flags/FC-AD@2x.png",
      "team_2": "Scotland",
      "team_2_flag": "https://d13ir53smqqeyp.cloudfront.net/flags/gl-flags/FC-LOC@2x.png",
      "banner": "https://www.fancode.com/skillup-uploads/cms-media/Alfred-Dunhill-Links-Championship_match_card_1.jpg",
      "stream_link": "https://dai.google.com/linear/hls/event/ym-ldso_TlalzETzuYc-ng/master.m3u8"
    }
  ]
}