{
  "type": "FanCode All Live Matches Data in Json",
  "generated_by": "Byte Capsule \nTelegram: https://t.me/J_9X_H_9X_N\nGithub:https://github.com/byte-capsule",
  "total_mathes": 4,
  "last_upaded": "20-11-2024 on 2:30:41 PM \ud83c\udf1e",
  "matches": [
    {
      "event_catagory": "cricket",
      "event_name": "Gujarat Women's Championship",
      "match_id": 113675,
      "match_name": "Garvi Women vs Victorious 11 Women",
      "team_1": "Garvi Women",
      "team_1_flag": "https://d13ir53smqqeyp.cloudfront.net/flags/cr-flags/FC-GRW@2x.png",
      "team_2": "Victorious 11 Women",
      "team_2_flag": "https://d13ir53smqqeyp.cloudfront.net/flags/cr-flags/FC-VW@2x.png",
      "banner": "https://www.fancode.com/skillup-uploads/fc-web-logo/fc-logo-orange-block-bg.png",
      "stream_link": "https://dai.google.com/linear/hls/event/J6Z4A4IBRmCRy_Be1vKZYw/master.m3u8"
    },
    {
      "event_catagory": "cricket",
      "event_name": "ECS Spain, Encore, 2024",
      "match_id": 113110,
      "match_name": "Pak Barcelona vs Pak I Care Badalona",
      "team_1": "Pak Barcelona",
      "team_1_flag": "https://d13ir53smqqeyp.cloudfront.net/flags/cr-flags/FC-PKB@2x.png",
      "team_2": "Pak I Care Badalona",
      "team_2_flag": "https://d13ir53smqqeyp.cloudfront.net/flags/cr-flags/FC-PIC@2x.png",
      "banner": "https://www.fancode.com/skillup-uploads/cms-media/113110_4641_PKB_PIC_fc-web.jpg",
      "stream_link": "https://dai.google.com/linear/hls/event/8Vn7ww_0SnCDqR5EfSFvdQ/master.m3u8"
    },
    {
      "event_catagory": "cricket",
      "event_name": "ICC Men's T20 World Cup Asia Qualifier B, 2024",
      "match_id": 112367,
      "match_name": "Bhutan vs Qatar",
      "team_1": "Bhutan",
      "team_1_flag": "https://d13ir53smqqeyp.cloudfront.net/flags/cr-flags/FC-BHU@2x.png",
      "team_2": "Qatar",
      "team_2_flag": "https://d13ir53smqqeyp.cloudfront.net/flags/cr-flags/FC-QTR@2x.png",
      "banner": "https://www.fancode.com/skillup-uploads/fc-web-logo/fc-logo-orange-block-bg.png",
      "stream_link": "https://dai.google.com/linear/hls/event/26Cp9f3mQHe_OatNoL8xxw/master.m3u8"
    },
    {
      "event_catagory": "cricket",
      "event_name": "ICC Men's T20 World Cup Asia Qualifier B, 2024",
      "match_id": 112366,
      "match_name": "Thailand vs Cambodia",
      "team_1": "Thailand",
      "team_1_flag": "https://d13ir53smqqeyp.cloudfront.net/flags/cr-flags/FC-THL@2x.png",
      "team_2": "Cambodia",
      "team_2_flag": "https://d13ir53smqqeyp.cloudfront.net/flags/cr-flags/FC-CAMB@2x.png",
      "banner": "https://www.fancode.com/skillup-uploads/fc-web-logo/fc-logo-orange-block-bg.png",
      "stream_link": "https://dai.google.com/linear/hls/event/ReDxzuyrRyiUceITZqtDcA/master.m3u8"
    }
  ]
}