{
  "type": "FanCode All Live Matches Data in Json",
  "generated_by": "Byte Capsule \nTelegram: https://t.me/J_9X_H_9X_N\nGithub:https://github.com/byte-capsule",
  "total_mathes": 4,
  "last_upaded": "04-12-2024 on 9:43:23 PM \ud83c\udf19",
  "matches": [
    {
      "event_catagory": "cricket",
      "event_name": "Dream11 Trinidad T10 Blast, 6th Edition, 2024",
      "match_id": 113573,
      "match_name": "Soca Kings vs Trillions System Ltd Strikers",
      "team_1": "Soca Kings",
      "team_1_flag": "https://d13ir53smqqeyp.cloudfront.net/flags/cr-flags/FC-SOCA@2x.png",
      "team_2": "Trillions System Ltd Strikers",
      "team_2_flag": "https://d13ir53smqqeyp.cloudfront.net/flags/cr-flags/FC-TLS@2x.png",
      "banner": "https://www.fancode.com/skillup-uploads/cms-media/113573_4653_TLS_SCK_fc-web.jpg",
      "stream_link": "https://dai.google.com/linear/hls/event/PoUv3z3jTZuMcIEc2na9tQ/master.m3u8"
    },
    {
      "event_catagory": "cricket",
      "event_name": "ECS Spain, Encore, 2024",
      "match_id": 113183,
      "match_name": "Royal Barcelona vs Girona",
      "team_1": "Royal Barcelona",
      "team_1_flag": "https://d13ir53smqqeyp.cloudfront.net/flags/cr-flags/FC-RB@2x.png",
      "team_2": "Girona",
      "team_2_flag": "https://d13ir53smqqeyp.cloudfront.net/flags/cr-flags/DEF-CR18@2x.png",
      "banner": "https://www.fancode.com/skillup-uploads/cms-media/113183_4641_RB_GIR_fc-web_1733232712795.jpg",
      "stream_link": "https://dai.google.com/linear/hls/event/VXlqgXd-QUiJlLgkr6bRkg/master.m3u8"
    },
    {
      "event_catagory": "football",
      "event_name": "AFC Champions League Two 2024-25",
      "match_id": 108746,
      "match_name": "Al Quwa Al Jawiya vs Al Taawoun",
      "team_1": "Al Quwa Al Jawiya",
      "team_1_flag": "https://d13ir53smqqeyp.cloudfront.net/flags/ft-flags/FC-AIRF@2x.png",
      "team_2": "Al Taawoun",
      "team_2_flag": "https://d13ir53smqqeyp.cloudfront.net/flags/ft-flags/FC-ALTW@2x.png",
      "banner": "https://www.fancode.com/skillup-uploads/cms-media/108746_4476_AFC_ALTW_fc-web.jpg",
      "stream_link": "https://dai.google.com/linear/hls/event/dZcJ7z0IRBikxTrnnW3VIA/master.m3u8"
    },
    {
      "event_catagory": "football",
      "event_name": "AFC Champions League Two 2024-25",
      "match_id": 108745,
      "match_name": "Khaldiya vs Altyn Asyr",
      "team_1": "Khaldiya",
      "team_1_flag": "https://d13ir53smqqeyp.cloudfront.net/flags/ft-flags/FC-KH@2x.png",
      "team_2": "Altyn Asyr",
      "team_2_flag": "https://d13ir53smqqeyp.cloudfront.net/flags/ft-flags/FC-ALTN@2x.png",
      "banner": "https://www.fancode.com/skillup-uploads/cms-media/108745_4476_KHA_AA_fc-web.jpg",
      "stream_link": "https://dai.google.com/linear/hls/event/mlMHvYWtSPuSlewEw9tqAw/master.m3u8"
    }
  ]
}